<?xml version="1.0" encoding="UTF-8"?>
<!DOCTYPE mapper PUBLIC "-//mybatis.org//DTD Mapper 3.0//EN" "http://mybatis.org/dtd/mybatis-3-mapper.dtd">
<mapper namespace="com.solo.erp.dao.mapper.ErpShopInfoMapper">
  <resultMap id="BaseResultMap" type="com.solo.erp.dao.model.ErpShopInfo">
    <!--
      WARNING - @mbg.generated
      This element is automatically generated by MyBatis Generator, do not modify.
      This element was generated on Fri Aug 03 15:33:38 CST 2018.
    -->
    <id column="id" jdbcType="INTEGER" property="id" />
    <result column="shop_name" jdbcType="VARCHAR" property="shopName" />
    <result column="shop_address" jdbcType="VARCHAR" property="shopAddress" />
    <result column="gmt_create" jdbcType="TIMESTAMP" property="gmtCreate" />
    <result column="gmt_modified" jdbcType="TIMESTAMP" property="gmtModified" />
    <result column="is_enable" jdbcType="BIT" property="isEnable" />
    <result column="parent_id" jdbcType="INTEGER" property="parentId" />
  </resultMap>
  <sql id="Example_Where_Clause">
    <!--
      WARNING - @mbg.generated
      This element is automatically generated by MyBatis Generator, do not modify.
      This element was generated on Fri Aug 03 15:33:38 CST 2018.
    -->
    <where>
      <foreach collection="oredCriteria" item="criteria" separator="or">
        <if test="criteria.valid">
          <trim prefix="(" prefixOverrides="and" suffix=")">
            <foreach collection="criteria.criteria" item="criterion">
              <choose>
                <when test="criterion.noValue">
                  and ${criterion.condition}
                </when>
                <when test="criterion.singleValue">
                  and ${criterion.condition} #{criterion.value}
                </when>
                <when test="criterion.betweenValue">
                  and ${criterion.condition} #{criterion.value} and #{criterion.secondValue}
                </when>
                <when test="criterion.listValue">
                  and ${criterion.condition}
                  <foreach close=")" collection="criterion.value" item="listItem" open="(" separator=",">
                    #{listItem}
                  </foreach>
                </when>
              </choose>
            </foreach>
          </trim>
        </if>
      </foreach>
    </where>
  </sql>
  <sql id="Update_By_Example_Where_Clause">
    <!--
      WARNING - @mbg.generated
      This element is automatically generated by MyBatis Generator, do not modify.
      This element was generated on Fri Aug 03 15:33:38 CST 2018.
    -->
    <where>
      <foreach collection="example.oredCriteria" item="criteria" separator="or">
        <if test="criteria.valid">
          <trim prefix="(" prefixOverrides="and" suffix=")">
            <foreach collection="criteria.criteria" item="criterion">
              <choose>
                <when test="criterion.noValue">
                  and ${criterion.condition}
                </when>
                <when test="criterion.singleValue">
                  and ${criterion.condition} #{criterion.value}
                </when>
                <when test="criterion.betweenValue">
                  and ${criterion.condition} #{criterion.value} and #{criterion.secondValue}
                </when>
                <when test="criterion.listValue">
                  and ${criterion.condition}
                  <foreach close=")" collection="criterion.value" item="listItem" open="(" separator=",">
                    #{listItem}
                  </foreach>
                </when>
              </choose>
            </foreach>
          </trim>
        </if>
      </foreach>
    </where>
  </sql>
  <sql id="Base_Column_List">
    <!--
      WARNING - @mbg.generated
      This element is automatically generated by MyBatis Generator, do not modify.
      This element was generated on Fri Aug 03 15:33:38 CST 2018.
    -->
    id, shop_name, shop_address, gmt_create, gmt_modified, is_enable, parent_id
  </sql>
  <select id="selectByExample" parameterType="com.solo.erp.dao.model.ErpShopInfoExample" resultMap="BaseResultMap">
    <!--
      WARNING - @mbg.generated
      This element is automatically generated by MyBatis Generator, do not modify.
      This element was generated on Fri Aug 03 15:33:38 CST 2018.
    -->
    select
    <if test="distinct">
      distinct
    </if>
    <include refid="Base_Column_List" />
    from erp_shop_info
    <if test="_parameter != null">
      <include refid="Example_Where_Clause" />
    </if>
    <if test="orderByClause != null">
      order by ${orderByClause}
    </if>
  </select>
  <select id="selectByPrimaryKey" parameterType="java.lang.Integer" resultMap="BaseResultMap">
    <!--
      WARNING - @mbg.generated
      This element is automatically generated by MyBatis Generator, do not modify.
      This element was generated on Fri Aug 03 15:33:38 CST 2018.
    -->
    select 
    <include refid="Base_Column_List" />
    from erp_shop_info
    where id = #{id,jdbcType=INTEGER}
  </select>
  <delete id="deleteByPrimaryKey" parameterType="java.lang.Integer">
    <!--
      WARNING - @mbg.generated
      This element is automatically generated by MyBatis Generator, do not modify.
      This element was generated on Fri Aug 03 15:33:38 CST 2018.
    -->
    delete from erp_shop_info
    where id = #{id,jdbcType=INTEGER}
  </delete>
  <delete id="deleteByExample" parameterType="com.solo.erp.dao.model.ErpShopInfoExample">
    <!--
      WARNING - @mbg.generated
      This element is automatically generated by MyBatis Generator, do not modify.
      This element was generated on Fri Aug 03 15:33:38 CST 2018.
    -->
    delete from erp_shop_info
    <if test="_parameter != null">
      <include refid="Example_Where_Clause" />
    </if>
  </delete>
  <insert id="insert" parameterType="com.solo.erp.dao.model.ErpShopInfo">
    <!--
      WARNING - @mbg.generated
      This element is automatically generated by MyBatis Generator, do not modify.
      This element was generated on Fri Aug 03 15:33:38 CST 2018.
    -->
    insert into erp_shop_info (id, shop_name, shop_address, 
      gmt_create, gmt_modified, is_enable, 
      parent_id)
    values (#{id,jdbcType=INTEGER}, #{shopName,jdbcType=VARCHAR}, #{shopAddress,jdbcType=VARCHAR}, 
      #{gmtCreate,jdbcType=TIMESTAMP}, #{gmtModified,jdbcType=TIMESTAMP}, #{isEnable,jdbcType=BIT}, 
      #{parentId,jdbcType=INTEGER})
  </insert>
  <insert id="insertSelective" parameterType="com.solo.erp.dao.model.ErpShopInfo">
    <!--
      WARNING - @mbg.generated
      This element is automatically generated by MyBatis Generator, do not modify.
      This element was generated on Fri Aug 03 15:33:38 CST 2018.
    -->
    insert into erp_shop_info
    <trim prefix="(" suffix=")" suffixOverrides=",">
      <if test="id != null">
        id,
      </if>
      <if test="shopName != null">
        shop_name,
      </if>
      <if test="shopAddress != null">
        shop_address,
      </if>
      <if test="gmtCreate != null">
        gmt_create,
      </if>
      <if test="gmtModified != null">
        gmt_modified,
      </if>
      <if test="isEnable != null">
        is_enable,
      </if>
      <if test="parentId != null">
        parent_id,
      </if>
    </trim>
    <trim prefix="values (" suffix=")" suffixOverrides=",">
      <if test="id != null">
        #{id,jdbcType=INTEGER},
      </if>
      <if test="shopName != null">
        #{shopName,jdbcType=VARCHAR},
      </if>
      <if test="shopAddress != null">
        #{shopAddress,jdbcType=VARCHAR},
      </if>
      <if test="gmtCreate != null">
        #{gmtCreate,jdbcType=TIMESTAMP},
      </if>
      <if test="gmtModified != null">
        #{gmtModified,jdbcType=TIMESTAMP},
      </if>
      <if test="isEnable != null">
        #{isEnable,jdbcType=BIT},
      </if>
      <if test="parentId != null">
        #{parentId,jdbcType=INTEGER},
      </if>
    </trim>
  </insert>
  <select id="countByExample" parameterType="com.solo.erp.dao.model.ErpShopInfoExample" resultType="java.lang.Long">
    <!--
      WARNING - @mbg.generated
      This element is automatically generated by MyBatis Generator, do not modify.
      This element was generated on Fri Aug 03 15:33:38 CST 2018.
    -->
    select count(*) from erp_shop_info
    <if test="_parameter != null">
      <include refid="Example_Where_Clause" />
    </if>
  </select>
  <update id="updateByExampleSelective" parameterType="map">
    <!--
      WARNING - @mbg.generated
      This element is automatically generated by MyBatis Generator, do not modify.
      This element was generated on Fri Aug 03 15:33:38 CST 2018.
    -->
    update erp_shop_info
    <set>
      <if test="record.id != null">
        id = #{record.id,jdbcType=INTEGER},
      </if>
      <if test="record.shopName != null">
        shop_name = #{record.shopName,jdbcType=VARCHAR},
      </if>
      <if test="record.shopAddress != null">
        shop_address = #{record.shopAddress,jdbcType=VARCHAR},
      </if>
      <if test="record.gmtCreate != null">
        gmt_create = #{record.gmtCreate,jdbcType=TIMESTAMP},
      </if>
      <if test="record.gmtModified != null">
        gmt_modified = #{record.gmtModified,jdbcType=TIMESTAMP},
      </if>
      <if test="record.isEnable != null">
        is_enable = #{record.isEnable,jdbcType=BIT},
      </if>
      <if test="record.parentId != null">
        parent_id = #{record.parentId,jdbcType=INTEGER},
      </if>
    </set>
    <if test="_parameter != null">
      <include refid="Update_By_Example_Where_Clause" />
    </if>
  </update>
  <update id="updateByExample" parameterType="map">
    <!--
      WARNING - @mbg.generated
      This element is automatically generated by MyBatis Generator, do not modify.
      This element was generated on Fri Aug 03 15:33:38 CST 2018.
    -->
    update erp_shop_info
    set id = #{record.id,jdbcType=INTEGER},
      shop_name = #{record.shopName,jdbcType=VARCHAR},
      shop_address = #{record.shopAddress,jdbcType=VARCHAR},
      gmt_create = #{record.gmtCreate,jdbcType=TIMESTAMP},
      gmt_modified = #{record.gmtModified,jdbcType=TIMESTAMP},
      is_enable = #{record.isEnable,jdbcType=BIT},
      parent_id = #{record.parentId,jdbcType=INTEGER}
    <if test="_parameter != null">
      <include refid="Update_By_Example_Where_Clause" />
    </if>
  </update>
  <update id="updateByPrimaryKeySelective" parameterType="com.solo.erp.dao.model.ErpShopInfo">
    <!--
      WARNING - @mbg.generated
      This element is automatically generated by MyBatis Generator, do not modify.
      This element was generated on Fri Aug 03 15:33:38 CST 2018.
    -->
    update erp_shop_info
    <set>
      <if test="shopName != null">
        shop_name = #{shopName,jdbcType=VARCHAR},
      </if>
      <if test="shopAddress != null">
        shop_address = #{shopAddress,jdbcType=VARCHAR},
      </if>
      <if test="gmtCreate != null">
        gmt_create = #{gmtCreate,jdbcType=TIMESTAMP},
      </if>
      <if test="gmtModified != null">
        gmt_modified = #{gmtModified,jdbcType=TIMESTAMP},
      </if>
      <if test="isEnable != null">
        is_enable = #{isEnable,jdbcType=BIT},
      </if>
      <if test="parentId != null">
        parent_id = #{parentId,jdbcType=INTEGER},
      </if>
    </set>
    where id = #{id,jdbcType=INTEGER}
  </update>
  <update id="updateByPrimaryKey" parameterType="com.solo.erp.dao.model.ErpShopInfo">
    <!--
      WARNING - @mbg.generated
      This element is automatically generated by MyBatis Generator, do not modify.
      This element was generated on Fri Aug 03 15:33:38 CST 2018.
    -->
    update erp_shop_info
    set shop_name = #{shopName,jdbcType=VARCHAR},
      shop_address = #{shopAddress,jdbcType=VARCHAR},
      gmt_create = #{gmtCreate,jdbcType=TIMESTAMP},
      gmt_modified = #{gmtModified,jdbcType=TIMESTAMP},
      is_enable = #{isEnable,jdbcType=BIT},
      parent_id = #{parentId,jdbcType=INTEGER}
    where id = #{id,jdbcType=INTEGER}
  </update>
  <select id="selectByExampleWithRowbounds" parameterType="com.solo.erp.dao.model.ErpShopInfoExample" resultMap="BaseResultMap">
    <!--
      WARNING - @mbg.generated
      This element is automatically generated by MyBatis Generator, do not modify.
      This element was generated on Fri Aug 03 15:33:38 CST 2018.
    -->
    select
    <if test="distinct">
      distinct
    </if>
    <include refid="Base_Column_List" />
    from erp_shop_info
    <if test="_parameter != null">
      <include refid="Example_Where_Clause" />
    </if>
    <if test="orderByClause != null">
      order by ${orderByClause}
    </if>
  </select>
</mapper>